epic_awesome_gamer/__init__.py
epic_awesome_gamer/collector.py
epic_awesome_gamer/epic_games.py
epic_awesome_gamer/types.py
epic_awesome_gamer/cli/__init__.py
epic_awesome_gamer/cli/main.py
epic_awesome_gamer/helper/__init__.py
epic_awesome_gamer/helper/env_generator.py
epic_awesome_gamer/helper/get_promotions.py
epic_awesome_gamer-0.4.1.dist-info/METADATA
epic_awesome_gamer-0.4.1.dist-info/WHEEL
epic_awesome_gamer-0.4.1.dist-info/entry_points.txt
epic_awesome_gamer-0.4.1.dist-info/licenses/LICENSE
epic_awesome_gamer-0.4.1.dist-info/RECORD
