Metadata-Version: 2.4
Name: epic-awesome-gamer
Version: 0.4.1
Summary: 🍷 Gracefully claim weekly free games from Epic Store.
Project-URL: Homepage, https://github.com/QIN2DIM/epic-awesome-gamer
Project-URL: Documentation, https://github.com/QIN2DIM/epic-awesome-gamer
Project-URL: Repository, https://github.com/QIN2DIM/epic-awesome-gamer.git
Project-URL: Issues, https://github.com/QIN2DIM/epic-awesome-gamer/issues
Project-URL: Changelog, https://github.com/QIN2DIM/epic-awesome-gamer/blob/master/CHANGELOG.md
Author-email: QIN2DIM <yaoqinse@gmail.com>
License-Expression: GPL-3.0-or-later
License-File: LICENSE
Keywords: epic,epic-awesome-gamer,epic-games-store
Classifier: Development Status :: 3 - Alpha
Classifier: Intended Audience :: Developers
Classifier: Programming Language :: Python :: 3
Classifier: Programming Language :: Python :: 3 :: Only
Classifier: Programming Language :: Python :: 3.10
Classifier: Programming Language :: Python :: 3.11
Classifier: Programming Language :: Python :: 3.12
Classifier: Programming Language :: Python :: 3.13
Classifier: Topic :: Scientific/Engineering :: Artificial Intelligence
Classifier: Topic :: Scientific/Engineering :: Image Processing
Classifier: Topic :: Scientific/Engineering :: Image Recognition
Classifier: Topic :: Software Development
Requires-Python: >=3.12
Requires-Dist: hcaptcha-challenger[camoufox]>=0.17.1
Requires-Dist: pydantic-settings>=2.8.1
